png_jpg/__init__.py
png_jpg/png_to_jpg.py
png_to_jpg-1.0.0.dist-info/METADATA
png_to_jpg-1.0.0.dist-info/WHEEL
png_to_jpg-1.0.0.dist-info/top_level.txt
png_to_jpg-1.0.0.dist-info/RECORD
