Metadata-Version: 2.1
Name: png-to-jpg
Version: 1.0.0
Summary: png to jpg
Author: Farooq
Keywords: python,jpg png,jpg
Requires-Dist: pillow
